googlecloudprofiler/builder.py
googlecloudprofiler/profile_pb2.py
googlecloudprofiler/_profiler.cpython-310-i386-linux-gnu.so
googlecloudprofiler/backoff.py
googlecloudprofiler/__init__.py
googlecloudprofiler/cpu_profiler.py
googlecloudprofiler/pythonprofiler.py
googlecloudprofiler/__version__.py
googlecloudprofiler/client.py
google_cloud_profiler_wheels-4.0.0.dist-info/WHEEL
google_cloud_profiler_wheels-4.0.0.dist-info/LICENSE
google_cloud_profiler_wheels-4.0.0.dist-info/top_level.txt
google_cloud_profiler_wheels-4.0.0.dist-info/RECORD
google_cloud_profiler_wheels-4.0.0.dist-info/METADATA
