Metadata-Version: 2.1
Name: google-cloud-profiler-wheels
Version: 4.0.0
Summary: Google Cloud Profiler Python Agent
Home-page: https://github.com/GoogleCloudPlatform/cloud-profiler-python
Author: Google LLC
License: Apache License, Version 2.0
Keywords: google cloud profiler
Platform: UNKNOWN
Classifier: Development Status :: 5 - Production/Stable
Classifier: Intended Audience :: Developers
Classifier: License :: OSI Approved :: Apache Software License
Classifier: Programming Language :: Python :: 3.6
Classifier: Programming Language :: Python :: 3.7
Classifier: Programming Language :: Python :: 3.8
Classifier: Programming Language :: Python :: 3.9
License-File: LICENSE
Requires-Dist: google-api-python-client (!=1.12.0,!=2.0.2)
Requires-Dist: google-auth (>=1.0.0)
Requires-Dist: google-auth-httplib2
Requires-Dist: protobuf
Requires-Dist: requests
